LICENSE.txt
MANIFEST.in
README.md
setup.py
scanninglaw/__init__.py
scanninglaw/asf.py
scanninglaw/config.py
scanninglaw/equirectangular_map.py
scanninglaw/fetch_utils.py
scanninglaw/healpix_map.py
scanninglaw/json_serializers.py
scanninglaw/map.py
scanninglaw/sfexceptions.py
scanninglaw/source.py
scanninglaw/std_paths.py
scanninglaw/times.py
scanninglaw/unstructured_map.py
scanninglaw.egg-info/PKG-INFO
scanninglaw.egg-info/SOURCES.txt
scanninglaw.egg-info/dependency_links.txt
scanninglaw.egg-info/not-zip-safe
scanninglaw.egg-info/requires.txt
scanninglaw.egg-info/top_level.txt
scanninglaw/data/Astrometry.csv
scanninglaw/data/Astrometry_dr3.csv
scanninglaw/data/Photometry.csv
scanninglaw/data/Spectroscopy.csv
scanninglaw/data/horizons_results_gaia.txt