Metadata-Version: 2.1
Name: scanninglaw
Version: 1.1.1
Summary: Easy-to-use portal to the Gaia scanning law.
Home-page: https://github.com/gaiaverse/scanninglaw
Author: Douglas Boubert
Author-email: douglasboubert@gmail.com
License: GPLv2
Download-URL: https://github.com/gaiaverse/scanninglaw/archive/v1.1.1.tar.gz
Platform: UNKNOWN
